<?xml version="1.0"?>
<mujoco model="scene_20">
	<compiler angle="radian" />
	<include file="include/settings.xml" />
	<asset>
		<include file="include/assets.xml" />
		<include file="robot/include/robot_assets.xml" />
	</asset>
	<include file="include/defaults.xml" />
	<include file="include/custom_attributes_for_shelf_2.xml" />
	<worldbody>
		<include file="include/camera_and_lighting.xml" />
		<body name="object_1" pos="0.345149 0.098241 0.182605" quat="0.980833 0.000000 -0.000003 -0.194850">
			<geom friction="0.3 0.3 0.3" contype="3" conaffinity="3" mass="1." name="object_1" rgba="1 0 0. 1" size="0.03 0.05" type="cylinder" />
			<joint damping="0.5" stiffness="0.01" armature="0.1" name="object_1_free" type="free" />
		</body>
		<body name="object_2" pos="0.348973 0.268894 0.182605" quat="-0.968573 0.000003 0.000006 0.248728">
			<geom friction="0.3 0.3 0.3" contype="3" conaffinity="3" mass="1." name="object_2" rgba="1 0 0. 1" size="0.03 0.05" type="cylinder" />
			<joint damping="0.5" stiffness="0.01" armature="0.1" name="object_2_free" type="free" />
		</body>
		<body name="object_3" pos="0.424681 -0.056537 0.182605" quat="-0.246444 -0.000003 -0.000001 0.969157">
			<geom friction="0.3 0.3 0.3" contype="3" conaffinity="3" mass="1." name="object_3" rgba="0 1 0. 1" size="0.03 0.05" type="cylinder" />
			<joint damping="0.5" stiffness="0.01" armature="0.1" name="object_3_free" type="free" />
		</body>
		<body name="object_4" pos="0.441431 0.081193 0.182603" quat="0.778525 0.000002 0.000003 -0.627614">
			<geom friction="0.3 0.3 0.3" contype="3" conaffinity="3" mass="1." name="object_4" rgba="1 0 0. 1" size="0.03 0.05" type="cylinder" />
			<joint damping="0.5" stiffness="0.01" armature="0.1" name="object_4_free" type="free" />
		</body>
		<body name="object_5" pos="0.271554 -0.081498 0.182603" quat="0.016214 -0.000002 -0.000007 -0.999869">
			<geom friction="0.3 0.3 0.3" contype="3" conaffinity="3" mass="1." name="object_5" rgba="1 0 0. 1" size="0.03 0.05" type="cylinder" />
			<joint damping="0.5" stiffness="0.01" armature="0.1" name="object_5_free" type="free" />
		</body>
		<body name="object_6" pos="0.279371 0.255249 0.182602" quat="0.274987 -0.000001 -0.000007 -0.961448">
			<geom friction="0.3 0.3 0.3" contype="3" conaffinity="3" mass="1." name="object_6" rgba="1 0 0. 1" size="0.03 0.05" type="cylinder" />
			<joint damping="0.5" stiffness="0.01" armature="0.1" name="object_6_free" type="free" />
		</body>
		<body name="object_7" pos="0.493458 0.258615 0.182600" quat="0.507764 -0.000007 0.000008 0.861496">
			<geom friction="0.3 0.3 0.3" contype="3" conaffinity="3" mass="1." name="object_7" rgba="1 0 0. 1" size="0.03 0.05" type="cylinder" />
			<joint damping="0.5" stiffness="0.01" armature="0.1" name="object_7_free" type="free" />
		</body>
		<body name="object_8" pos="0.553233 0.122799 0.182598" quat="0.793106 -0.000012 -0.000002 0.609084">
			<geom friction="0.3 0.3 0.3" contype="3" conaffinity="3" mass="1." name="object_8" rgba="1 0 0. 1" size="0.03 0.05" type="cylinder" />
			<joint damping="0.5" stiffness="0.01" armature="0.1" name="object_8_free" type="free" />
		</body>
		<body name="object_9" pos="0.403572 -0.235684 0.182596" quat="-0.845484 -0.000006 0.000004 0.534000">
			<geom friction="0.3 0.3 0.3" contype="3" conaffinity="3" mass="1." name="object_9" rgba="1 0 0. 1" size="0.03 0.05" type="cylinder" />
			<joint damping="0.5" stiffness="0.01" armature="0.1" name="object_9_free" type="free" />
		</body>
		<body name="object_10" pos="0.369354 -0.114691 0.182594" quat="0.872763 0.000002 -0.000003 0.488144">
			<geom friction="0.3 0.3 0.3" contype="3" conaffinity="3" mass="1." name="object_10" rgba="1 0 0. 1" size="0.03 0.05" type="cylinder" />
			<joint damping="0.5" stiffness="0.01" armature="0.1" name="object_10_free" type="free" />
		</body>
		<body name="object_11" pos="0.427948 0.231648 0.182591" quat="-0.953918 0.000004 -0.000007 0.300069">
			<geom friction="0.3 0.3 0.3" contype="3" conaffinity="3" mass="1." name="object_11" rgba="1 0 0. 1" size="0.03 0.05" type="cylinder" />
			<joint damping="0.5" stiffness="0.01" armature="0.1" name="object_11_free" type="free" />
		</body>
		<body name="object_12" pos="0.312092 -0.295715 0.182587" quat="0.448812 -0.000008 -0.000013 0.893626">
			<geom friction="0.3 0.3 0.3" contype="3" conaffinity="3" mass="1." name="object_12" rgba="1 0 0. 1" size="0.03 0.05" type="cylinder" />
			<joint damping="0.5" stiffness="0.01" armature="0.1" name="object_12_free" type="free" />
		</body>
		<body name="object_13" pos="0.493826 -0.086117 0.182583" quat="-0.847640 0.000003 0.000002 -0.530572">
			<geom friction="0.3 0.3 0.3" contype="3" conaffinity="3" mass="1." name="object_13" rgba="1 0 0. 1" size="0.03 0.05" type="cylinder" />
			<joint damping="0.5" stiffness="0.01" armature="0.1" name="object_13_free" type="free" />
		</body>
		<body name="object_14" pos="0.505833 -0.222541 0.182579" quat="-0.468706 0.000013 -0.000007 0.883354">
			<geom friction="0.3 0.3 0.3" contype="3" conaffinity="3" mass="1." name="object_14" rgba="1 0 0. 1" size="0.03 0.05" type="cylinder" />
			<joint damping="0.5" stiffness="0.01" armature="0.1" name="object_14_free" type="free" />
		</body>
		<body name="object_15" pos="0.317966 0.155917 0.182575" quat="-0.962288 0.000005 0.000011 -0.272034">
			<geom friction="0.3 0.3 0.3" contype="3" conaffinity="3" mass="1." name="object_15" rgba="1 0 0. 1" size="0.03 0.05" type="cylinder" />
			<joint damping="0.5" stiffness="0.01" armature="0.1" name="object_15_free" type="free" />
		</body>
		<body name="object_16" pos="0.346979 0.340591 0.182570" quat="-0.809333 0.000005 0.000012 0.587350">
			<geom friction="0.3 0.3 0.3" contype="3" conaffinity="3" mass="1." name="object_16" rgba="1 0 0. 1" size="0.03 0.05" type="cylinder" />
			<joint damping="0.5" stiffness="0.01" armature="0.1" name="object_16_free" type="free" />
		</body>
		<body name="object_17" pos="0.510681 -0.027532 0.182564" quat="-0.901921 -0.000000 -0.000014 -0.431902">
			<geom friction="0.3 0.3 0.3" contype="3" conaffinity="3" mass="1." name="object_17" rgba="1 0 0. 1" size="0.03 0.05" type="cylinder" />
			<joint damping="0.5" stiffness="0.01" armature="0.1" name="object_17_free" type="free" />
		</body>
		<body name="object_18" pos="0.297513 -0.211410 0.182559" quat="0.400590 -0.000008 -0.000005 0.916258">
			<geom friction="0.3 0.3 0.3" contype="3" conaffinity="3" mass="1." name="object_18" rgba="1 0 0. 1" size="0.03 0.05" type="cylinder" />
			<joint damping="0.5" stiffness="0.01" armature="0.1" name="object_18_free" type="free" />
		</body>
		<body name="object_19" pos="0.289366 0.028849 0.182554" quat="0.770921 -0.000006 -0.000006 -0.636930">
			<geom friction="0.3 0.3 0.3" contype="3" conaffinity="3" mass="1." name="object_19" rgba="1 0 0. 1" size="0.03 0.05" type="cylinder" />
			<joint damping="0.5" stiffness="0.01" armature="0.1" name="object_19_free" type="free" />
		</body>
		<body name="object_20" pos="0.459194 -0.141162 0.182549" quat="-0.875568 0.000001 -0.000000 0.483095">
			<geom friction="0.3 0.3 0.3" contype="3" conaffinity="3" mass="1." name="object_20" rgba="1 0 0. 1" size="0.03 0.05" type="cylinder" />
			<joint damping="0.5" stiffness="0.01" armature="0.1" name="object_20_free" type="free" />
		</body>
		<include file="robot/include/gripper_only_planar_robot.xml" />
		<include file="include/small_shelf.xml" />
	</worldbody>
</mujoco>
