<?xml version="1.0"?>
<mujoco model="scene_20">
	<compiler angle="radian" />
	<include file="include/settings.xml" />
	<asset>
		<include file="include/assets.xml" />
		<include file="robot/include/robot_assets.xml" />
	</asset>
	<include file="include/defaults.xml" />
	<include file="include/custom_attributes_for_shelf_2.xml" />
	<worldbody>
		<include file="include/camera_and_lighting.xml" />
		<body name="object_1" pos="0.368550 0.094313 0.182613" quat="0.999326 0.000001 -0.000006 0.036711">
			<geom friction="0.3 0.3 0.3" contype="3" conaffinity="3" mass="1." name="object_1" rgba="1 0 0. 1" size="0.03 0.05" type="cylinder" />
			<joint damping="0.5" stiffness="0.01" armature="0.1" name="object_1_free" type="free" />
		</body>
		<body name="object_2" pos="0.442381 0.074645 0.182613" quat="0.805113 -0.000003 0.000002 0.593121">
			<geom friction="0.3 0.3 0.3" contype="3" conaffinity="3" mass="1." name="object_2" rgba="1 0 0. 1" size="0.03 0.05" type="cylinder" />
			<joint damping="0.5" stiffness="0.01" armature="0.1" name="object_2_free" type="free" />
		</body>
		<body name="object_3" pos="0.487924 -0.194960 0.182612" quat="0.562774 -0.000004 0.000013 -0.826611">
			<geom friction="0.3 0.3 0.3" contype="3" conaffinity="3" mass="1." name="object_3" rgba="0 1 0. 1" size="0.03 0.05" type="cylinder" />
			<joint damping="0.5" stiffness="0.01" armature="0.1" name="object_3_free" type="free" />
		</body>
		<body name="object_4" pos="0.304645 0.120676 0.182610" quat="-0.973068 0.000014 0.000002 0.230519">
			<geom friction="0.3 0.3 0.3" contype="3" conaffinity="3" mass="1." name="object_4" rgba="1 0 0. 1" size="0.03 0.05" type="cylinder" />
			<joint damping="0.5" stiffness="0.01" armature="0.1" name="object_4_free" type="free" />
		</body>
		<body name="object_5" pos="0.534514 0.179683 0.182608" quat="-0.986995 0.000007 -0.000010 0.160750">
			<geom friction="0.3 0.3 0.3" contype="3" conaffinity="3" mass="1." name="object_5" rgba="1 0 0. 1" size="0.03 0.05" type="cylinder" />
			<joint damping="0.5" stiffness="0.01" armature="0.1" name="object_5_free" type="free" />
		</body>
		<body name="object_6" pos="0.302554 0.060219 0.182605" quat="-0.932898 0.000004 -0.000002 -0.360141">
			<geom friction="0.3 0.3 0.3" contype="3" conaffinity="3" mass="1." name="object_6" rgba="1 0 0. 1" size="0.03 0.05" type="cylinder" />
			<joint damping="0.5" stiffness="0.01" armature="0.1" name="object_6_free" type="free" />
		</body>
		<body name="object_7" pos="0.429219 -0.071870 0.182602" quat="0.653737 -0.000006 -0.000001 -0.756721">
			<geom friction="0.3 0.3 0.3" contype="3" conaffinity="3" mass="1." name="object_7" rgba="1 0 0. 1" size="0.03 0.05" type="cylinder" />
			<joint damping="0.5" stiffness="0.01" armature="0.1" name="object_7_free" type="free" />
		</body>
		<body name="object_8" pos="0.494132 0.112823 0.182598" quat="0.857226 0.000000 -0.000001 0.514940">
			<geom friction="0.3 0.3 0.3" contype="3" conaffinity="3" mass="1." name="object_8" rgba="1 0 0. 1" size="0.03 0.05" type="cylinder" />
			<joint damping="0.5" stiffness="0.01" armature="0.1" name="object_8_free" type="free" />
		</body>
		<body name="object_9" pos="0.378599 -0.193315 0.182593" quat="-0.419322 0.000002 -0.000000 0.907838">
			<geom friction="0.3 0.3 0.3" contype="3" conaffinity="3" mass="1." name="object_9" rgba="1 0 0. 1" size="0.03 0.05" type="cylinder" />
			<joint damping="0.5" stiffness="0.01" armature="0.1" name="object_9_free" type="free" />
		</body>
		<body name="object_10" pos="0.481956 -0.007860 0.182588" quat="-0.261561 0.000011 0.000015 -0.965187">
			<geom friction="0.3 0.3 0.3" contype="3" conaffinity="3" mass="1." name="object_10" rgba="1 0 0. 1" size="0.03 0.05" type="cylinder" />
			<joint damping="0.5" stiffness="0.01" armature="0.1" name="object_10_free" type="free" />
		</body>
		<body name="object_11" pos="0.318060 -0.067252 0.182582" quat="-0.592261 -0.000002 -0.000001 0.805746">
			<geom friction="0.3 0.3 0.3" contype="3" conaffinity="3" mass="1." name="object_11" rgba="1 0 0. 1" size="0.03 0.05" type="cylinder" />
			<joint damping="0.5" stiffness="0.01" armature="0.1" name="object_11_free" type="free" />
		</body>
		<body name="object_12" pos="0.539576 -0.096860 0.182575" quat="0.920819 0.000001 0.000000 0.389989">
			<geom friction="0.3 0.3 0.3" contype="3" conaffinity="3" mass="1." name="object_12" rgba="1 0 0. 1" size="0.03 0.05" type="cylinder" />
			<joint damping="0.5" stiffness="0.01" armature="0.1" name="object_12_free" type="free" />
		</body>
		<body name="object_13" pos="0.377163 0.154144 0.182567" quat="0.231675 0.000004 0.000000 0.972793">
			<geom friction="0.3 0.3 0.3" contype="3" conaffinity="3" mass="1." name="object_13" rgba="1 0 0. 1" size="0.03 0.05" type="cylinder" />
			<joint damping="0.5" stiffness="0.01" armature="0.1" name="object_13_free" type="free" />
		</body>
		<body name="object_14" pos="0.535815 0.067572 0.182558" quat="0.935506 -0.000001 0.000014 0.353312">
			<geom friction="0.3 0.3 0.3" contype="3" conaffinity="3" mass="1." name="object_14" rgba="1 0 0. 1" size="0.03 0.05" type="cylinder" />
			<joint damping="0.5" stiffness="0.01" armature="0.1" name="object_14_free" type="free" />
		</body>
		<body name="object_15" pos="0.318332 -0.177996 0.182549" quat="-0.928962 -0.000002 0.000005 0.370176">
			<geom friction="0.3 0.3 0.3" contype="3" conaffinity="3" mass="1." name="object_15" rgba="1 0 0. 1" size="0.03 0.05" type="cylinder" />
			<joint damping="0.5" stiffness="0.01" armature="0.1" name="object_15_free" type="free" />
		</body>
		<body name="object_16" pos="0.404069 -0.015728 0.182539" quat="-0.514634 -0.000003 -0.000012 0.857410">
			<geom friction="0.3 0.3 0.3" contype="3" conaffinity="3" mass="1." name="object_16" rgba="1 0 0. 1" size="0.03 0.05" type="cylinder" />
			<joint damping="0.5" stiffness="0.01" armature="0.1" name="object_16_free" type="free" />
		</body>
		<body name="object_17" pos="0.465045 0.185002 0.182527" quat="0.961024 0.000002 -0.000002 -0.276463">
			<geom friction="0.3 0.3 0.3" contype="3" conaffinity="3" mass="1." name="object_17" rgba="1 0 0. 1" size="0.03 0.05" type="cylinder" />
			<joint damping="0.5" stiffness="0.01" armature="0.1" name="object_17_free" type="free" />
		</body>
		<body name="object_18" pos="0.334934 -0.005651 0.182516" quat="-0.657771 0.000005 0.000003 -0.753218">
			<geom friction="0.3 0.3 0.3" contype="3" conaffinity="3" mass="1." name="object_18" rgba="1 0 0. 1" size="0.03 0.05" type="cylinder" />
			<joint damping="0.5" stiffness="0.01" armature="0.1" name="object_18_free" type="free" />
		</body>
		<body name="object_19" pos="0.542608 -0.159756 0.182505" quat="-0.142538 -0.000006 -0.000000 -0.989789">
			<geom friction="0.3 0.3 0.3" contype="3" conaffinity="3" mass="1." name="object_19" rgba="1 0 0. 1" size="0.03 0.05" type="cylinder" />
			<joint damping="0.5" stiffness="0.01" armature="0.1" name="object_19_free" type="free" />
		</body>
		<body name="object_20" pos="0.455024 -0.128543 0.182495" quat="0.254845 0.000000 0.000001 0.966982">
			<geom friction="0.3 0.3 0.3" contype="3" conaffinity="3" mass="1." name="object_20" rgba="1 0 0. 1" size="0.03 0.05" type="cylinder" />
			<joint damping="0.5" stiffness="0.01" armature="0.1" name="object_20_free" type="free" />
		</body>
		<include file="robot/include/gripper_only_planar_robot.xml" />
		<include file="include/small_shelf.xml" />
	</worldbody>
</mujoco>
