<?xml version="1.0"?>
<mujoco model="scene_20">
	<compiler angle="radian" />
	<include file="include/settings.xml" />
	<asset>
		<include file="include/assets.xml" />
		<include file="robot/include/robot_assets.xml" />
	</asset>
	<include file="include/defaults.xml" />
	<include file="include/custom_attributes_for_shelf_2.xml" />
	<worldbody>
		<include file="include/camera_and_lighting.xml" />
		<body name="object_1" pos="0.353221 0.084174 0.182613" quat="-0.960961 0.000005 -0.000001 0.276683">
			<geom friction="0.3 0.3 0.3" contype="3" conaffinity="3" mass="1." name="object_1" rgba="1 0 0. 1" size="0.03 0.05" type="cylinder" />
			<joint damping="0.5" stiffness="0.01" armature="0.1" name="object_1_free" type="free" />
		</body>
		<body name="object_2" pos="0.432866 0.069426 0.182613" quat="0.572233 0.000001 -0.000006 0.820091">
			<geom friction="0.3 0.3 0.3" contype="3" conaffinity="3" mass="1." name="object_2" rgba="1 0 0. 1" size="0.03 0.05" type="cylinder" />
			<joint damping="0.5" stiffness="0.01" armature="0.1" name="object_2_free" type="free" />
		</body>
		<body name="object_3" pos="0.475763 -0.192555 0.182612" quat="-0.990018 -0.000005 -0.000012 -0.140939">
			<geom friction="0.3 0.3 0.3" contype="3" conaffinity="3" mass="1." name="object_3" rgba="0 1 0. 1" size="0.03 0.05" type="cylinder" />
			<joint damping="0.5" stiffness="0.01" armature="0.1" name="object_3_free" type="free" />
		</body>
		<body name="object_4" pos="0.513054 0.191153 0.182610" quat="-0.847388 0.000008 -0.000006 0.530974">
			<geom friction="0.3 0.3 0.3" contype="3" conaffinity="3" mass="1." name="object_4" rgba="1 0 0. 1" size="0.03 0.05" type="cylinder" />
			<joint damping="0.5" stiffness="0.01" armature="0.1" name="object_4_free" type="free" />
		</body>
		<body name="object_5" pos="0.502313 0.102212 0.182608" quat="-0.005333 0.000009 0.000000 -0.999986">
			<geom friction="0.3 0.3 0.3" contype="3" conaffinity="3" mass="1." name="object_5" rgba="1 0 0. 1" size="0.03 0.05" type="cylinder" />
			<joint damping="0.5" stiffness="0.01" armature="0.1" name="object_5_free" type="free" />
		</body>
		<body name="object_6" pos="0.380107 -0.086225 0.182605" quat="0.675825 -0.000008 -0.000004 -0.737062">
			<geom friction="0.3 0.3 0.3" contype="3" conaffinity="3" mass="1." name="object_6" rgba="1 0 0. 1" size="0.03 0.05" type="cylinder" />
			<joint damping="0.5" stiffness="0.01" armature="0.1" name="object_6_free" type="free" />
		</body>
		<body name="object_7" pos="0.448540 -0.077361 0.182602" quat="-0.385688 -0.000000 0.000001 0.922629">
			<geom friction="0.3 0.3 0.3" contype="3" conaffinity="3" mass="1." name="object_7" rgba="1 0 0. 1" size="0.03 0.05" type="cylinder" />
			<joint damping="0.5" stiffness="0.01" armature="0.1" name="object_7_free" type="free" />
		</body>
		<body name="object_8" pos="0.307969 -0.066928 0.182598" quat="-0.570667 -0.000005 -0.000002 0.821181">
			<geom friction="0.3 0.3 0.3" contype="3" conaffinity="3" mass="1." name="object_8" rgba="1 0 0. 1" size="0.03 0.05" type="cylinder" />
			<joint damping="0.5" stiffness="0.01" armature="0.1" name="object_8_free" type="free" />
		</body>
		<body name="object_9" pos="0.388231 -0.187427 0.182593" quat="-0.570814 -0.000007 -0.000007 -0.821079">
			<geom friction="0.3 0.3 0.3" contype="3" conaffinity="3" mass="1." name="object_9" rgba="1 0 0. 1" size="0.03 0.05" type="cylinder" />
			<joint damping="0.5" stiffness="0.01" armature="0.1" name="object_9_free" type="free" />
		</body>
		<body name="object_10" pos="0.537833 -0.085286 0.182588" quat="0.699499 -0.000011 0.000004 -0.714633">
			<geom friction="0.3 0.3 0.3" contype="3" conaffinity="3" mass="1." name="object_10" rgba="1 0 0. 1" size="0.03 0.05" type="cylinder" />
			<joint damping="0.5" stiffness="0.01" armature="0.1" name="object_10_free" type="free" />
		</body>
		<body name="object_11" pos="0.502131 0.011576 0.182582" quat="-0.736048 0.000003 -0.000004 0.676929">
			<geom friction="0.3 0.3 0.3" contype="3" conaffinity="3" mass="1." name="object_11" rgba="1 0 0. 1" size="0.03 0.05" type="cylinder" />
			<joint damping="0.5" stiffness="0.01" armature="0.1" name="object_11_free" type="free" />
		</body>
		<body name="object_12" pos="0.365158 0.181011 0.182575" quat="0.859593 0.000006 -0.000001 -0.510980">
			<geom friction="0.3 0.3 0.3" contype="3" conaffinity="3" mass="1." name="object_12" rgba="1 0 0. 1" size="0.03 0.05" type="cylinder" />
			<joint damping="0.5" stiffness="0.01" armature="0.1" name="object_12_free" type="free" />
		</body>
		<body name="object_13" pos="0.381599 -0.013558 0.182567" quat="-0.961738 0.000001 0.000001 0.273972">
			<geom friction="0.3 0.3 0.3" contype="3" conaffinity="3" mass="1." name="object_13" rgba="1 0 0. 1" size="0.03 0.05" type="cylinder" />
			<joint damping="0.5" stiffness="0.01" armature="0.1" name="object_13_free" type="free" />
		</body>
		<body name="object_14" pos="0.305701 0.155781 0.182558" quat="0.652593 -0.000010 -0.000013 0.757708">
			<geom friction="0.3 0.3 0.3" contype="3" conaffinity="3" mass="1." name="object_14" rgba="1 0 0. 1" size="0.03 0.05" type="cylinder" />
			<joint damping="0.5" stiffness="0.01" armature="0.1" name="object_14_free" type="free" />
		</body>
		<body name="object_15" pos="0.331958 -0.126622 0.182549" quat="0.278465 -0.000004 -0.000011 0.960446">
			<geom friction="0.3 0.3 0.3" contype="3" conaffinity="3" mass="1." name="object_15" rgba="1 0 0. 1" size="0.03 0.05" type="cylinder" />
			<joint damping="0.5" stiffness="0.01" armature="0.1" name="object_15_free" type="free" />
		</body>
		<body name="object_16" pos="0.545922 -0.199834 0.182539" quat="0.992281 -0.000012 0.000017 -0.124013">
			<geom friction="0.3 0.3 0.3" contype="3" conaffinity="3" mass="1." name="object_16" rgba="1 0 0. 1" size="0.03 0.05" type="cylinder" />
			<joint damping="0.5" stiffness="0.01" armature="0.1" name="object_16_free" type="free" />
		</body>
		<body name="object_17" pos="0.449891 0.185814 0.182527" quat="0.998875 0.000005 -0.000002 0.047430">
			<geom friction="0.3 0.3 0.3" contype="3" conaffinity="3" mass="1." name="object_17" rgba="1 0 0. 1" size="0.03 0.05" type="cylinder" />
			<joint damping="0.5" stiffness="0.01" armature="0.1" name="object_17_free" type="free" />
		</body>
		<body name="object_18" pos="0.304068 0.007807 0.182516" quat="-0.997153 0.000000 0.000007 0.075402">
			<geom friction="0.3 0.3 0.3" contype="3" conaffinity="3" mass="1." name="object_18" rgba="1 0 0. 1" size="0.03 0.05" type="cylinder" />
			<joint damping="0.5" stiffness="0.01" armature="0.1" name="object_18_free" type="free" />
		</body>
		<body name="object_19" pos="0.483033 -0.130544 0.182505" quat="-0.993029 -0.000003 0.000001 -0.117874">
			<geom friction="0.3 0.3 0.3" contype="3" conaffinity="3" mass="1." name="object_19" rgba="1 0 0. 1" size="0.03 0.05" type="cylinder" />
			<joint damping="0.5" stiffness="0.01" armature="0.1" name="object_19_free" type="free" />
		</body>
		<body name="object_20" pos="0.304568 -0.193691 0.182495" quat="0.945858 0.000000 0.000000 0.324580">
			<geom friction="0.3 0.3 0.3" contype="3" conaffinity="3" mass="1." name="object_20" rgba="1 0 0. 1" size="0.03 0.05" type="cylinder" />
			<joint damping="0.5" stiffness="0.01" armature="0.1" name="object_20_free" type="free" />
		</body>
		<include file="robot/include/gripper_only_planar_robot.xml" />
		<include file="include/small_shelf.xml" />
	</worldbody>
</mujoco>
