<?xml version="1.0"?>
<mujoco model="scene_20">
	<compiler angle="radian" />
	<include file="include/settings.xml" />
	<asset>
		<include file="include/assets.xml" />
		<include file="robot/include/robot_assets.xml" />
	</asset>
	<include file="include/defaults.xml" />
	<include file="include/custom_attributes_for_shelf_2.xml" />
	<worldbody>
		<include file="include/camera_and_lighting.xml" />
		<body name="object_1" pos="0.321813 0.301613 0.182613" quat="-0.865653 0.000002 -0.000002 0.500645">
			<geom friction="0.3 0.3 0.3" contype="3" conaffinity="3" mass="1." name="object_1" rgba="1 0 0. 1" size="0.03 0.05" type="cylinder" />
			<joint damping="0.5" stiffness="0.01" armature="0.1" name="object_1_free" type="free" />
		</body>
		<body name="object_2" pos="0.400571 0.292187 0.182613" quat="0.487201 -0.000007 -0.000002 -0.873290">
			<geom friction="0.3 0.3 0.3" contype="3" conaffinity="3" mass="1." name="object_2" rgba="1 0 0. 1" size="0.03 0.05" type="cylinder" />
			<joint damping="0.5" stiffness="0.01" armature="0.1" name="object_2_free" type="free" />
		</body>
		<body name="object_3" pos="0.493134 -0.136010 0.182612" quat="0.986478 0.000017 -0.000007 -0.163896">
			<geom friction="0.3 0.3 0.3" contype="3" conaffinity="3" mass="1." name="object_3" rgba="0 1 0. 1" size="0.03 0.05" type="cylinder" />
			<joint damping="0.5" stiffness="0.01" armature="0.1" name="object_3_free" type="free" />
		</body>
		<body name="object_4" pos="0.543437 -0.337234 0.182609" quat="-0.381997 -0.000006 -0.000002 -0.924164">
			<geom friction="0.3 0.3 0.3" contype="3" conaffinity="3" mass="1." name="object_4" rgba="1 0 0. 1" size="0.03 0.05" type="cylinder" />
			<joint damping="0.5" stiffness="0.01" armature="0.1" name="object_4_free" type="free" />
		</body>
		<body name="object_5" pos="0.516775 0.202487 0.182608" quat="-0.128052 0.000011 -0.000002 0.991767">
			<geom friction="0.3 0.3 0.3" contype="3" conaffinity="3" mass="1." name="object_5" rgba="1 0 0. 1" size="0.03 0.05" type="cylinder" />
			<joint damping="0.5" stiffness="0.01" armature="0.1" name="object_5_free" type="free" />
		</body>
		<body name="object_6" pos="0.280848 0.085311 0.182605" quat="0.965227 -0.000007 -0.000005 0.261413">
			<geom friction="0.3 0.3 0.3" contype="3" conaffinity="3" mass="1." name="object_6" rgba="1 0 0. 1" size="0.03 0.05" type="cylinder" />
			<joint damping="0.5" stiffness="0.01" armature="0.1" name="object_6_free" type="free" />
		</body>
		<body name="object_7" pos="0.539687 0.134541 0.182602" quat="-0.305211 0.000013 -0.000007 0.952285">
			<geom friction="0.3 0.3 0.3" contype="3" conaffinity="3" mass="1." name="object_7" rgba="1 0 0. 1" size="0.03 0.05" type="cylinder" />
			<joint damping="0.5" stiffness="0.01" armature="0.1" name="object_7_free" type="free" />
		</body>
		<body name="object_8" pos="0.361306 -0.111398 0.182599" quat="-0.999965 -0.000002 -0.000008 0.008335">
			<geom friction="0.3 0.3 0.3" contype="3" conaffinity="3" mass="1." name="object_8" rgba="1 0 0. 1" size="0.03 0.05" type="cylinder" />
			<joint damping="0.5" stiffness="0.01" armature="0.1" name="object_8_free" type="free" />
		</body>
		<body name="object_9" pos="0.526427 0.332595 0.182593" quat="-0.500808 -0.000005 -0.000006 -0.865558">
			<geom friction="0.3 0.3 0.3" contype="3" conaffinity="3" mass="1." name="object_9" rgba="1 0 0. 1" size="0.03 0.05" type="cylinder" />
			<joint damping="0.5" stiffness="0.01" armature="0.1" name="object_9_free" type="free" />
		</body>
		<body name="object_10" pos="0.309641 -0.240181 0.182588" quat="0.339002 -0.000010 -0.000013 0.940786">
			<geom friction="0.3 0.3 0.3" contype="3" conaffinity="3" mass="1." name="object_10" rgba="1 0 0. 1" size="0.03 0.05" type="cylinder" />
			<joint damping="0.5" stiffness="0.01" armature="0.1" name="object_10_free" type="free" />
		</body>
		<body name="object_11" pos="0.420401 -0.073354 0.182582" quat="-0.670006 0.000001 -0.000004 0.742355">
			<geom friction="0.3 0.3 0.3" contype="3" conaffinity="3" mass="1." name="object_11" rgba="1 0 0. 1" size="0.03 0.05" type="cylinder" />
			<joint damping="0.5" stiffness="0.01" armature="0.1" name="object_11_free" type="free" />
		</body>
		<body name="object_12" pos="0.440678 -0.202347 0.182575" quat="0.161787 0.000002 -0.000001 0.986826">
			<geom friction="0.3 0.3 0.3" contype="3" conaffinity="3" mass="1." name="object_12" rgba="1 0 0. 1" size="0.03 0.05" type="cylinder" />
			<joint damping="0.5" stiffness="0.01" armature="0.1" name="object_12_free" type="free" />
		</body>
		<body name="object_13" pos="0.382854 0.175724 0.182567" quat="0.285387 0.000000 -0.000006 -0.958412">
			<geom friction="0.3 0.3 0.3" contype="3" conaffinity="3" mass="1." name="object_13" rgba="1 0 0. 1" size="0.03 0.05" type="cylinder" />
			<joint damping="0.5" stiffness="0.01" armature="0.1" name="object_13_free" type="free" />
		</body>
		<body name="object_14" pos="0.378049 0.098285 0.182558" quat="0.092856 0.000000 -0.000002 -0.995680">
			<geom friction="0.3 0.3 0.3" contype="3" conaffinity="3" mass="1." name="object_14" rgba="1 0 0. 1" size="0.03 0.05" type="cylinder" />
			<joint damping="0.5" stiffness="0.01" armature="0.1" name="object_14_free" type="free" />
		</body>
		<body name="object_15" pos="0.467292 0.040822 0.182549" quat="-0.353323 0.000003 0.000002 -0.935502">
			<geom friction="0.3 0.3 0.3" contype="3" conaffinity="3" mass="1." name="object_15" rgba="1 0 0. 1" size="0.03 0.05" type="cylinder" />
			<joint damping="0.5" stiffness="0.01" armature="0.1" name="object_15_free" type="free" />
		</body>
		<body name="object_16" pos="0.506297 -0.058850 0.182538" quat="0.995432 0.000006 -0.000000 0.095475">
			<geom friction="0.3 0.3 0.3" contype="3" conaffinity="3" mass="1." name="object_16" rgba="1 0 0. 1" size="0.03 0.05" type="cylinder" />
			<joint damping="0.5" stiffness="0.01" armature="0.1" name="object_16_free" type="free" />
		</body>
		<body name="object_17" pos="0.295612 -0.158852 0.182527" quat="-0.479169 0.000008 -0.000003 -0.877723">
			<geom friction="0.3 0.3 0.3" contype="3" conaffinity="3" mass="1." name="object_17" rgba="1 0 0. 1" size="0.03 0.05" type="cylinder" />
			<joint damping="0.5" stiffness="0.01" armature="0.1" name="object_17_free" type="free" />
		</body>
		<body name="object_18" pos="0.317694 0.003950 0.182516" quat="-0.862667 -0.000002 0.000002 0.505771">
			<geom friction="0.3 0.3 0.3" contype="3" conaffinity="3" mass="1." name="object_18" rgba="1 0 0. 1" size="0.03 0.05" type="cylinder" />
			<joint damping="0.5" stiffness="0.01" armature="0.1" name="object_18_free" type="free" />
		</body>
		<body name="object_19" pos="0.285495 0.171134 0.182505" quat="0.689743 -0.000003 -0.000007 0.724054">
			<geom friction="0.3 0.3 0.3" contype="3" conaffinity="3" mass="1." name="object_19" rgba="1 0 0. 1" size="0.03 0.05" type="cylinder" />
			<joint damping="0.5" stiffness="0.01" armature="0.1" name="object_19_free" type="free" />
		</body>
		<body name="object_20" pos="0.288121 -0.335948 0.182495" quat="0.584743 0.000003 -0.000000 -0.811219">
			<geom friction="0.3 0.3 0.3" contype="3" conaffinity="3" mass="1." name="object_20" rgba="1 0 0. 1" size="0.03 0.05" type="cylinder" />
			<joint damping="0.5" stiffness="0.01" armature="0.1" name="object_20_free" type="free" />
		</body>
		<include file="robot/include/gripper_only_planar_robot.xml" />
		<include file="include/small_shelf.xml" />
	</worldbody>
</mujoco>
